yadtcommons
