Metadata-Version: 1.1
Name: yadtcommons
Version: 0.0.7
Summary: commons libary for YADT
Home-page: https://github.com/yadt/yadtcommons
Author: Marcel Wolf, Maximilien Riehl, Michael Gruber
Author-email: marcel.wolf@immobilienscout24.de, maximilien.riehl@gmail.com, aelgru@gmail.com
License: GNU GPL v3
Platform: UNKNOWN
Classifier: Development Status :: 3 - Alpha
Classifier: Programming Language :: Python
